hlskit_py/__init__.py
hlskit_py/py.typed
hlskit_py/models/__init__.py
hlskit_py/models/hls_video.py
hlskit_py/models/hls_video_processing_settings.py
hlskit_py/services/__init__.py
hlskit_py/services/hls_video_processor.py
hlskit_py/tools/__init__.py
hlskit_py/tools/ffmpeg_command_builder.py
hlskit_py/tools/m3u8_tools.py
hlskit_py-0.1.3.dist-info/METADATA
hlskit_py-0.1.3.dist-info/WHEEL
hlskit_py-0.1.3.dist-info/licenses/LICENSE
hlskit_py-0.1.3.dist-info/RECORD
