Metadata-Version: 2.4
Name: hlskit-py
Version: 0.1.3
Summary: HlsKit provides strong HLS video conversion features backed by ffmpeg. Prepare your mp4 files for streaming
Project-URL: Homepage, https://github.com/like-engels/hlskit-py
Author-email: Engels Ruehl <higashikataengels@icloud.com>
License: GNU LESSER GENERAL PUBLIC LICENSE
License-File: LICENSE
Keywords: cloudfront,ffmpeg,hls,mp4,multimedia,streaming,transcoding,video,video compression
Classifier: License :: OSI Approved :: GNU Lesser General Public License v3 or later (LGPLv3+)
Classifier: Programming Language :: Python
Classifier: Programming Language :: Python :: 3
Classifier: Topic :: Multimedia
Classifier: Topic :: Multimedia :: Video
Classifier: Topic :: Multimedia :: Video :: Conversion
Classifier: Topic :: Software Development
Requires-Python: >=3.12
Requires-Dist: pydantic>=2.10.5
Requires-Dist: ruff>=0.9.1
